LICENSE
MANIFEST.in
README.rst
buildout.cfg
requirements.txt
setup.py
version.txt
bob/__init__.py
bob.ip.tensorflow_extractor.egg-info/PKG-INFO
bob.ip.tensorflow_extractor.egg-info/SOURCES.txt
bob.ip.tensorflow_extractor.egg-info/dependency_links.txt
bob.ip.tensorflow_extractor.egg-info/requires.txt
bob.ip.tensorflow_extractor.egg-info/top_level.txt
bob/__pycache__/__init__.cpython-37.pyc
bob/ip/__init__.py
bob/ip/tensorflow_extractor/Extractor.py
bob/ip/tensorflow_extractor/FaceNet.py
bob/ip/tensorflow_extractor/MTCNN.py
bob/ip/tensorflow_extractor/__init__.py
bob/ip/tensorflow_extractor/test.py
bob/ip/tensorflow_extractor/data/mtcnn/mtcnn.hdf5
bob/ip/tensorflow_extractor/data/mtcnn/mtcnn.json
bob/ip/tensorflow_extractor/data/mtcnn/mtcnn.pb
bob/ip/tensorflow_extractor/data/mtcnn/test_image.png
doc/conf.py
doc/face_detect.rst
doc/guide.rst
doc/index.rst
doc/py_api.rst
doc/plot/detect_faces_mtcnn.py